airfoileditor/__init__.py
airfoileditor/__main__.py
airfoileditor/app.py
airfoileditor/app_model.py
airfoileditor/app_modes.py
airfoileditor/resources.py
airfoileditor/base/__init__.py
airfoileditor/base/app_utils.py
airfoileditor/base/artist.py
airfoileditor/base/common_utils.py
airfoileditor/base/diagram.py
airfoileditor/base/math_util.py
airfoileditor/base/panels.py
airfoileditor/base/spline.py
airfoileditor/base/widgets.py
airfoileditor/model/__init__.py
airfoileditor/model/airfoil.py
airfoileditor/model/airfoil_examples.py
airfoileditor/model/airfoil_geometry.py
airfoileditor/model/case.py
airfoileditor/model/polar_set.py
airfoileditor/model/xo2_controller.py
airfoileditor/model/xo2_driver.py
airfoileditor/model/xo2_input.py
airfoileditor/model/xo2_results.py
airfoileditor/ui/ae_artists.py
airfoileditor/ui/ae_diagrams.py
airfoileditor/ui/ae_dialogs.py
airfoileditor/ui/ae_panels.py
airfoileditor/ui/ae_widgets.py
airfoileditor/ui/util_dialogs.py
airfoileditor/ui/xo2_artists.py
airfoileditor/ui/xo2_diagrams.py
airfoileditor/ui/xo2_dialogs.py
airfoileditor/ui/xo2_panels.py
airfoileditor/assets/windows/worker.exe
airfoileditor/assets/windows/xoptfoil2.exe
airfoileditor/examples_optimize/F3B_bezier/F3B_bezier.xo2
airfoileditor/examples_optimize/F3B_bezier/Readme.txt
airfoileditor/examples_optimize/F3B_bezier/Seed_rearloaded.dat
airfoileditor/examples_optimize/F3B_bezier/make.bat
airfoileditor/examples_optimize/F3B_bezier/make.sh
airfoileditor/examples_optimize/F3B_bezier/stop.bat
airfoileditor/examples_optimize/F3F_hicks_henne/F3F_hicks_henne.xo2
airfoileditor/examples_optimize/F3F_hicks_henne/Readme.txt
airfoileditor/examples_optimize/F3F_hicks_henne/Seed_no_rearload.dat
airfoileditor/examples_optimize/F3F_hicks_henne/make.bat
airfoileditor/examples_optimize/F3F_hicks_henne/make.sh
airfoileditor/examples_optimize/F3F_hicks_henne/stop.bat
airfoileditor/examples_optimize/SD7003_fast/Readme.txt
airfoileditor/examples_optimize/SD7003_fast/SD7003.dat
airfoileditor-4.2.4.dist-info/METADATA
airfoileditor-4.2.4.dist-info/WHEEL
airfoileditor-4.2.4.dist-info/entry_points.txt
airfoileditor-4.2.4.dist-info/licenses/LICENSE
airfoileditor-4.2.4.dist-info/RECORD
