Metadata-Version: 2.4
Name: airfoileditor
Version: 4.2.4
Summary: View, Modify, Optimize Airfoils
Project-URL: Homepage, https://github.com/jxjo/AirfoilEditor
Project-URL: Issues, https://github.com/jxjo/AirfoilEditor/issues
Author-email: Jochen Guenzel <jochen@jxjo.de>
License-Expression: MIT
License-File: LICENSE
Classifier: Intended Audience :: End Users/Desktop
Classifier: Operating System :: OS Independent
Classifier: Programming Language :: Python :: 3.12
Classifier: Programming Language :: Python :: 3.13
Requires-Python: >=3.12
Requires-Dist: f90nml>=1.4.4
Requires-Dist: numpy>=2.2
Requires-Dist: packaging>=24.0
Requires-Dist: platformdirs>=4.3.0
Requires-Dist: pyqt6>=6.10.1
Requires-Dist: pyqtgraph>=0.13.7
Requires-Dist: requests
Requires-Dist: termcolor>=2.3.0
